ctkcolorpicker/__init__.py
ctkcolorpicker/main.py
CustomTkinter_ColorPicker-1.0.1.dist-info/METADATA
CustomTkinter_ColorPicker-1.0.1.dist-info/WHEEL
CustomTkinter_ColorPicker-1.0.1.dist-info/top_level.txt
CustomTkinter_ColorPicker-1.0.1.dist-info/RECORD
