Metadata-Version: 2.1
Name: CustomTkinter-ColorPicker
Version: 1.0.1
Summary: Simple color picker for customtkinter :)
Home-page: https://github.com/DDavid701/ctkcolorpicker
Author: DDavid701
Author-email: ddavid701@gmail.com
Classifier: Programming Language :: Python :: 3
Classifier: License :: OSI Approved :: MIT License
Classifier: Operating System :: OS Independent
Requires-Python: >=3.10
Requires-Dist: customtkinter
